caslake/__init__.py
caslake/migrate.py
caslake/symlink.py
caslake-0.1.0.dist-info/METADATA
caslake-0.1.0.dist-info/WHEEL
caslake-0.1.0.dist-info/RECORD
