Metadata-Version: 2.1
Name: caslake
Version: 0.1.0
Summary: 
License: GPL-3.0-only
Author: Vladislav Wohlrath
Author-email: vladislav@wohlrath.cz
Requires-Python: >=3.11,<4.0
Classifier: License :: OSI Approved :: GNU General Public License v3 (GPLv3)
Classifier: Programming Language :: Python :: 3
Classifier: Programming Language :: Python :: 3.11
Requires-Dist: SQLAlchemy (>=2.0.36,<3.0.0)
Requires-Dist: fsspec (>=2024.10.0,<2025.0.0)
Requires-Dist: sqlmodel (>=0.0.22,<0.0.23)
